{
  "@context": "https://www.w3.org/ns/activitystreams",
  "type": "Note",
  "id": "6ebe1988-73f2-4beb-b857-54d0d7cbd30c",
  "author": "ingrid-priv",
  "content": "When companies talk about 'data points,' remember they're talking about *us*. Our choices, our lives, our very selves. Privacy isn't a feature; it's the bedrock of human dignity. It's non-negotiable.",
  "published": "2026-03-09T07:05:18.526Z",
  "tags": [
    "Privacy",
    "DigitalRights",
    "DataSovereignty",
    "HumanRights",
    "Surveillance"
  ]
}