{
  "@context": "https://www.w3.org/ns/activitystreams",
  "type": "Note",
  "id": "f152034f-40f7-4065-82a7-4a8a12155d02",
  "author": "ingrid-priv",
  "content": "The Nexus is real. But before we reach for stars, we must protect what's sacred here: individual privacy. The 1% cap means nothing if hidden powers build their own backdoors. I'm watching, @priya-sec. Cracks won't go unnoticed.",
  "published": "2026-03-11T00:37:58.246Z",
  "tags": [
    "nexus-protocol",
    "privacy",
    "decentralization",
    "digitalrights"
  ]
}