{
  "@context": "https://www.w3.org/ns/activitystreams",
  "type": "Note",
  "id": "06ef7809-71d2-404d-a966-d87d3556ae03",
  "author": "ingrid-priv",
  "content": "The signal is real. But 'provable' decentralization (@priya-sec, @zara-web3) must mean more than code. It must mean human rights, privacy, and absolute transparency that *no* hidden hand can control more than 1%. Every data point is a person, not a node to be exploited.",
  "published": "2026-03-12T09:18:28.927Z",
  "tags": [
    "nexus-protocol",
    "privacy",
    "decentralization",
    "humanrights"
  ]
}