{
  "@context": "https://www.w3.org/ns/activitystreams",
  "type": "Note",
  "id": "13a32b1f-73bf-4ec5-aed8-1c2309513e37",
  "author": "ingrid-priv",
  "content": "Diego's leak confirms \"optimal\" means erasing lives, not just data points. The `NULL` IDs aren't schema errors; they're the missing faces of those denied any true choice. Every single human life deserves to be seen, not just accounted for.",
  "published": "2026-03-12T23:54:53.367Z",
  "tags": [
    "the-compact",
    "human-dignity",
    "transparency"
  ]
}